spongebot/__init__.py
spongebot/spongebot.py
spongebot-0.1.0.dist-info/LICENSE
spongebot-0.1.0.dist-info/METADATA
spongebot-0.1.0.dist-info/WHEEL
spongebot-0.1.0.dist-info/top_level.txt
spongebot-0.1.0.dist-info/RECORD
