Metadata-Version: 2.1
Name: spongebot
Version: 0.1.0
Summary: Monitor a directory for new files
Home-page: https://github.com/SirSolim/spongebot
Author: Nicolas Forstner
Author-email: nicolasforstner@yahoo.de
License: MIT
Platform: UNKNOWN
Classifier: License :: OSI Approved :: MIT License
Classifier: Programming Language :: Python :: 3
Classifier: Programming Language :: Python :: 3.7
